gunicorn_healthz_filter/__init__.py
gunicorn_healthz_filter-1.0.dist-info/LICENSE
gunicorn_healthz_filter-1.0.dist-info/METADATA
gunicorn_healthz_filter-1.0.dist-info/WHEEL
gunicorn_healthz_filter-1.0.dist-info/top_level.txt
gunicorn_healthz_filter-1.0.dist-info/RECORD
